cacao_password_generator/__init__.py
cacao_password_generator/cli.py
cacao_password_generator/config.py
cacao_password_generator/core.py
cacao_password_generator/rating.py
cacao_password_generator/utils.py
cacao_password_generator/validate.py
cacao_password_generator-1.0.2.dist-info/METADATA
cacao_password_generator-1.0.2.dist-info/WHEEL
cacao_password_generator-1.0.2.dist-info/entry_points.txt
cacao_password_generator-1.0.2.dist-info/top_level.txt
cacao_password_generator-1.0.2.dist-info/RECORD
