Metadata-Version: 2.4
Name: cacao-password-generator
Version: 1.0.2
Summary: A secure password generator with configurable constraints and strength rating
Author-email: Juan Denis <juan@vene.co>
License: MIT
Project-URL: Homepage, https://github.com/cacao-research/cacao-password-generator
Project-URL: Bug Reports, https://github.com/cacao-research/cacao-password-generator/issues
Project-URL: Source, https://github.com/cacao-research/cacao-password-generator
Keywords: password,generator,security,cryptography
Classifier: Development Status :: 4 - Beta
Classifier: Intended Audience :: Developers
Classifier: License :: OSI Approved :: MIT License
Classifier: Operating System :: OS Independent
Classifier: Programming Language :: Python :: 3
Classifier: Programming Language :: Python :: 3.8
Classifier: Programming Language :: Python :: 3.9
Classifier: Programming Language :: Python :: 3.10
Classifier: Programming Language :: Python :: 3.11
Classifier: Programming Language :: Python :: 3.12
Classifier: Topic :: Security
Classifier: Topic :: Software Development :: Libraries :: Python Modules
Classifier: Topic :: Utilities
Requires-Python: >=3.8
Provides-Extra: dev
Requires-Dist: pytest>=7.0; extra == "dev"
Requires-Dist: pytest-cov>=4.0; extra == "dev"
Requires-Dist: black>=22.0; extra == "dev"
Requires-Dist: flake8>=5.0; extra == "dev"
Requires-Dist: mypy>=1.0; extra == "dev"
